terramcp/__init__.py
terramcp/__main__.py
terramcp/server.py
terramcp-0.1.5.dist-info/METADATA
terramcp-0.1.5.dist-info/WHEEL
terramcp-0.1.5.dist-info/entry_points.txt
terramcp-0.1.5.dist-info/licenses/LICENSE
terramcp-0.1.5.dist-info/RECORD
