Metadata-Version: 2.4
Name: terramcp
Version: 0.1.5
Summary: Terra Dashboard MCP - A MCP server for managing your Terra Dashboard.
Author-email: Terra Team <dev@tryterra.co>, Sim Shang En <shangen@tryterra.co>
License: MIT
License-File: LICENSE
Requires-Python: >=3.12
Requires-Dist: fastmcp>=2.3.3
Requires-Dist: requests>=2.32.3
